LICENSE.md
README.md
pyproject.toml
setup.cfg
setup.py
bin/gen_xdds_file
bin/id22sumalle
bin/id22sume
bin/zingit
src/ewoksid22/__init__.py
src/ewoksid22/convert.py
src/ewoksid22/dirutils.py
src/ewoksid22/extract.py
src/ewoksid22/h5_to_spec.py
src/ewoksid22/id22sum.py
src/ewoksid22/rebin.py
src/ewoksid22/roitools.py
src/ewoksid22/specutils.py
src/ewoksid22/sum.py
src/ewoksid22/topas_extract.py
src/ewoksid22/wait.py
src/ewoksid22.egg-info/PKG-INFO
src/ewoksid22.egg-info/SOURCES.txt
src/ewoksid22.egg-info/dependency_links.txt
src/ewoksid22.egg-info/entry_points.txt
src/ewoksid22.egg-info/requires.txt
src/ewoksid22.egg-info/top_level.txt
src/ewoksid22/bin/__init__.py
src/ewoksid22/bin/__main__.py
src/ewoksid22/bin/id22sumalle
src/ewoksid22/bin/id22sume
src/ewoksid22/tests/__init__.py
src/ewoksid22/tests/test_dirutils.py
src/ewoksid22/tests/test_id22sum.py
src/ewoksid22/tests/test_roitools.py
src/ewoksid22/tests/test_script.py